logloss_beraf/__init__.py
logloss_beraf/__init__.pyc
logloss_beraf/config.yaml
logloss_beraf/settings.py
logloss_beraf/model_ops/__init__.py
logloss_beraf/model_ops/__init__.pyc
logloss_beraf/model_ops/applier.py
logloss_beraf/model_ops/classifiers.py
logloss_beraf/model_ops/trainer.py
logloss_beraf/model_ops/trainer.pyc
logloss_beraf/model_train/__init__.py
logloss_beraf/model_train/classifiers.py
logloss_beraf/model_train/trainer.py
logloss_beraf/resources/test_annotation.csv
logloss_beraf/resources/test_config.yaml
logloss_beraf/resources/test_features.csv
logloss_beraf/resources/trained_model
logloss_beraf/tests/__init__.py
logloss_beraf/tests/__init__.pyc
logloss_beraf/tests/test_model_train.py
logloss_beraf/tests/__pycache__/test_model_train.cpython-27-PYTEST.pyc
logloss_beraf/utils/__init__.py
logloss_beraf/utils/__init__.pyc
logloss_beraf/utils/constants.py
logloss_beraf/utils/constants.pyc
logloss_beraf/utils/load_data.py
logloss_beraf/utils/rnb_set_to_csv.py
logloss_beraf/visualisation/__init__.py
logloss_beraf/visualisation/__init__.pyc
logloss_beraf/visualisation/plotting.py
logloss_beraf/visualisation/plotting.pyc
logloss_beraf/visualization/__init__.py
logloss_beraf/visualization/plotting.py
logloss_beraf-0.7.dist-info/DESCRIPTION.rst
logloss_beraf-0.7.dist-info/METADATA
logloss_beraf-0.7.dist-info/RECORD
logloss_beraf-0.7.dist-info/WHEEL
logloss_beraf-0.7.dist-info/entry_points.txt
logloss_beraf-0.7.dist-info/metadata.json
logloss_beraf-0.7.dist-info/top_level.txt
