Metadata-Version: 2.0
Name: logloss-beraf
Version: 0.7
Summary: A tool for costructing a limited sized diagnostic panels based on methylation data
Home-page: UNKNOWN
Author: dezzan
Author-email: dezzandev@gmail.com
License: GPLv3
Keywords: model machine learning diagnostic panel methylation
Platform: UNKNOWN
Classifier: Development Status :: 4 - Beta
Classifier: Programming Language :: Python
Requires-Dist: bokeh (==0.12.2)
Requires-Dist: matplotlib
Requires-Dist: pandas (==0.18.1)
Requires-Dist: pytest
Requires-Dist: pytest-cov
Requires-Dist: pyyaml
Requires-Dist: scikit-learn (==0.18.1)
Requires-Dist: seaborn (==0.7.1)
Requires-Dist: statsmodels (==0.6.1)
